MailTMClient.py
MailTMClient-0.0.5.dist-info/METADATA
MailTMClient-0.0.5.dist-info/WHEEL
MailTMClient-0.0.5.dist-info/top_level.txt
MailTMClient-0.0.5.dist-info/RECORD
