Metadata-Version: 2.1
Name: MailTMClient
Version: 0.0.5
Summary: A Client to easily interact with the MailTM API
Home-page: https://github.com/RPwnage/MailTMClient
Author: Luca
License: UNKNOWN
Project-URL: Documentation, https://github.com/RPwnage/MailTMClient
Project-URL: Bug Reports, https://github.com/RPwnage/MailTMClient/issues
Project-URL: Source Code, https://github.com/RPwnage/MailTMClient
Platform: UNKNOWN
Classifier: Programming Language :: Python :: 3
Classifier: License :: OSI Approved :: MIT License
Classifier: Operating System :: OS Independent
Requires-Python: >=3.6
